pattern_buffer/__init__.py
pattern_buffer/core.py
pattern_buffer-0.0.4.dist-info/LICENSE
pattern_buffer-0.0.4.dist-info/METADATA
pattern_buffer-0.0.4.dist-info/WHEEL
pattern_buffer-0.0.4.dist-info/top_level.txt
pattern_buffer-0.0.4.dist-info/RECORD
