Metadata-Version: 2.1
Name: pattern_buffer
Version: 0.0.4
Summary: Fast pattern counting on small-alphabet sequences with GPU acceleration
Author-email: James Ashford <ashfordj@rocketmail.com>
Project-URL: Homepage, https://github.com/JELAshford/pattern-buffer
Classifier: Programming Language :: Python :: 3
Classifier: License :: OSI Approved :: MIT License
Classifier: Operating System :: OS Independent
Requires-Python: >=3.8
License-File: LICENSE
Requires-Dist: einops >=0.6.1
Requires-Dist: torch >=1.91
Requires-Dist: numpy <2
